StreamChatAgent.py
__init__.py
streamchat_agent-1.0.2.dist-info/LICENSE
streamchat_agent-1.0.2.dist-info/METADATA
streamchat_agent-1.0.2.dist-info/WHEEL
streamchat_agent-1.0.2.dist-info/top_level.txt
streamchat_agent-1.0.2.dist-info/RECORD
