Metadata-Version: 2.1
Name: streamchat-agent
Version: 1.0.2
Summary: Get YouTube chat comments with minimum time lag
Home-page: https://github.com/GeneralYadoc/StreamChatAgent
Author: General Yadoc
Author-email: 133023047+GeneralYadoc@users.noreply.github.com
License: MIT
Platform: UNKNOWN
Classifier: Development Status :: 4 - Beta
Classifier: Programming Language :: Python
Classifier: Programming Language :: Python :: 3.7
Classifier: Programming Language :: Python :: 3.8
Classifier: Programming Language :: Python :: 3.9
Classifier: License :: OSI Approved :: MIT License
License-File: LICENSE
Requires-Dist: pytchat (==0.5.5)
